pulse/__init__.py
pulse/errors.py
pulse/pulse.py
pulse/types.py
pulsesec-0.0.5.dist-info/METADATA
pulsesec-0.0.5.dist-info/WHEEL
pulsesec-0.0.5.dist-info/licenses/LICENSE
pulsesec-0.0.5.dist-info/RECORD
