Metadata-Version: 2.3
Name: pulsesec
Version: 0.0.5
Summary: Pulse Security - Python SDK
Project-URL: Homepage, https://github.com/pulsesec/pulse-sdk-py
Project-URL: Issues, https://github.com/pulsesec/pulse-sdk-py/issues
Author-email: Pulse Security <contact@pulsesecurity.org>
License-File: LICENSE
Requires-Python: >=3.8
Requires-Dist: aiohttp
Requires-Dist: dataclass-wizard
